ez_setup.py
setup.py
setuptools-0.6c9-py2.5.egg
HTTP4Store/HTTP4Store.py
HTTP4Store/__init__.py
HTTP4Store/sparql_response.py
HTTP4Store/utils.py
HTTP4Store.egg-info/PKG-INFO
HTTP4Store.egg-info/SOURCES.txt
HTTP4Store.egg-info/dependency_links.txt
HTTP4Store.egg-info/requires.txt
HTTP4Store.egg-info/top_level.txt
HTTP4Store/examples/basic_example.py
HTTP4Store/examples/rdfxml_add_append_delete.py