Metadata-Version: 1.0
Name: HTTP4Store
Version: 0.3
Summary: HTTP4Store - python client for 4Store.org (4s-httpd)
Home-page: UNKNOWN
Author: Ben O'Steen
Author-email: bosteen@gmail.com
License: UNKNOWN
Platform: UNKNOWN
